{
  "paths": {
    "/shippinglog": {
      "get": {
        "summary": "Get all shipping log records",
        "tags": ["ShippingLog"],
        "responses": {
          "200": {
            "description": "List of shipping log records",
            "content": {
              "application/json": {
                "schema": {"$ref": "#/components/schemas/ShippingLogArray"}
              }
            }
          }
        }
      },
      "post": {
        "summary": "Create a shipping log record",
        "tags": ["ShippingLog"],
        "requestBody": {
          "required": true,
          "content": {
            "application/json": {
              "schema": {"$ref": "#/components/schemas/ShippingLog"}
            }
          }
        },
        "responses": {
          "201": {"description": "Created"}
        }
      }
    },
    "/shippinglog/{id}": {
      "get": {
        "summary": "Get a shipping log record by ID",
        "tags": ["ShippingLog"],
        "parameters": [{"name": "id", "in": "path", "required": true, "schema": {"type": "integer"}}],
        "responses": {
          "200": {"description": "Shipping log record", "content": {"application/json": {"schema": {"$ref": "#/components/schemas/ShippingLog"}}}},
          "404": {"description": "Not found"}
        }
      },
      "put": {
        "summary": "Update a shipping log record",
        "tags": ["ShippingLog"],
        "parameters": [{"name": "id", "in": "path", "required": true, "schema": {"type": "integer"}}],
        "requestBody": {
          "required": true,
          "content": {"application/json": {"schema": {"$ref": "#/components/schemas/ShippingLog"}}}
        },
        "responses": {"200": {"description": "Updated"}, "404": {"description": "Not found"}}
      },
      "delete": {
        "summary": "Delete a shipping log record",
        "tags": ["ShippingLog"],
        "parameters": [{"name": "id", "in": "path", "required": true, "schema": {"type": "integer"}}],
        "responses": {"204": {"description": "Deleted"}, "404": {"description": "Not found"}}
      }
    }
  },
  "components": {
    "schemas": {
      "ShippingLog": {
        "type": "object",
        "properties": {
          "id": {"type": "integer"},
          "sales_id": {"type": "integer"},
          "carrier": {"type": "string"},
          "tracking_number": {"type": "string"},
          "status": {"type": "string"},
          "shipped_date": {"type": "string", "format": "date-time"},
          "delivered_date": {"type": "string", "format": "date-time"},
          "notes": {"type": "string"},
          "created_at": {"type": "string", "format": "date-time"},
          "updated_at": {"type": "string", "format": "date-time"}
        },
        "required": ["sales_id"]
      },
      "ShippingLogArray": {
        "type": "array",
        "items": {"$ref": "#/components/schemas/ShippingLog"}
      }
    }
  }
}
